clients/__init__.py
clients/base.py
clients/catcher.py
clients/glovo.py
clients/ubereats.py
tests/__init__.py
tests/test_functions.py
tests/test_clients/__init__.py
tests/test_clients/test_catcher.py
tests/test_clients/test_glovo.py
tests/test_clients/test_ubereats.py
pylivery-0.0.1.dist-info/METADATA
pylivery-0.0.1.dist-info/WHEEL
pylivery-0.0.1.dist-info/top_level.txt
pylivery-0.0.1.dist-info/RECORD
