Metadata-Version: 2.1
Name: pylivery
Version: 0.0.1
Summary: A package to integrate your business with delivery companies
Author: Aitor Poquet
Author-email: aitorpoquetgin@gmail.com
License: MIT
Keywords: delivery
Classifier: Development Status :: 3 - Alpha
Classifier: Intended Audience :: Developers
Classifier: License :: OSI Approved :: MIT License
Classifier: Programming Language :: Python :: 3
